partition/__init__.py
partition/code_generator.py
partition/dice.py
partition/interface.py
autodice-1.0.3.dev2.dist-info/LICENSE.txt
autodice-1.0.3.dev2.dist-info/METADATA
autodice-1.0.3.dev2.dist-info/WHEEL
autodice-1.0.3.dev2.dist-info/entry_points.txt
autodice-1.0.3.dev2.dist-info/top_level.txt
autodice-1.0.3.dev2.dist-info/RECORD
