Metadata-Version: 2.1
Name: autodice
Version: 1.0.3.dev2
Summary: Automated Distributed CNN inference at the Edge
Home-page: https://github.com/parrotsky/AutoDiCE
Author: Parrotsky
Author-email: x.guo3@uva.nl
Project-URL: Bug Reports, https://github.com/parrotsky/AutoDiCE/issues
Project-URL: Funding, https://donate.pypi.org
Project-URL: Say Thanks!, https://github.com/parrotsky/AutoDiCE
Project-URL: Source, https://github.com/parrotsky/AutoDiCE
Keywords: CodeGeneration,Deep Learning,development
Classifier: Development Status :: 3 - Alpha
Classifier: Intended Audience :: Developers
Classifier: Topic :: Software Development :: Build Tools
Classifier: License :: OSI Approved :: MIT License
Classifier: Programming Language :: Python :: 3
Classifier: Programming Language :: Python :: 3.7
Classifier: Programming Language :: Python :: 3.8
Classifier: Programming Language :: Python :: 3.9
Classifier: Programming Language :: Python :: 3.10
Classifier: Programming Language :: Python :: 3 :: Only
Requires-Python: >=3.1, <4
License-File: LICENSE.txt
Requires-Dist: onnx
Requires-Dist: numpy
Provides-Extra: dev
Requires-Dist: check-manifest ; extra == 'dev'
Provides-Extra: test
Requires-Dist: coverage ; extra == 'test'
